{
  "project": "avery-pay-platform",
  "generated_at": "2026-04-05T07:37:21.722Z",
  "total_recommendations": 2,
  "recommendations": [
    {
      "page": "/",
      "schema_type": "WebSite",
      "priority": "high",
      "fields": [
        "name",
        "url",
        "description",
        "potentialAction (SearchAction)"
      ]
    },
    {
      "page": "(all deep routes)",
      "schema_type": "BreadcrumbList",
      "priority": "medium",
      "fields": [
        "itemListElement[].name",
        "itemListElement[].item"
      ]
    }
  ]
}